MANIFEST.in
README.rst
VERSION
setup.py
hitchhttp/__init__.py
hitchhttp/commandline.py
hitchhttp/config.py
hitchhttp/http_request.py
hitchhttp/http_server_service.py
hitchhttp/main_request_handler.py
hitchhttp/mock_rest_uri.py
hitchhttp/monitor.py
hitchhttp/status_codes.py
hitchhttp/utils.py
hitchhttp.egg-info/PKG-INFO
hitchhttp.egg-info/SOURCES.txt
hitchhttp.egg-info/dependency_links.txt
hitchhttp.egg-info/entry_points.txt
hitchhttp.egg-info/not-zip-safe
hitchhttp.egg-info/requires.txt
hitchhttp.egg-info/top_level.txt
hitchhttp/templates/http.html
hitchhttp/templates/main.html
hitchhttp/templates/milligram-1.1.0.min.css